odoo/addons/hr_timesheet_report_milestone/README.rst
odoo/addons/hr_timesheet_report_milestone/__init__.py
odoo/addons/hr_timesheet_report_milestone/__manifest__.py
odoo/addons/hr_timesheet_report_milestone/i18n/hr_timesheet_milestone.pot
odoo/addons/hr_timesheet_report_milestone/i18n/hr_timesheet_report_milestone.pot
odoo/addons/hr_timesheet_report_milestone/i18n/it.po
odoo/addons/hr_timesheet_report_milestone/models/__init__.py
odoo/addons/hr_timesheet_report_milestone/models/account_analytic_line.py
odoo/addons/hr_timesheet_report_milestone/readme/CONTRIBUTORS.rst
odoo/addons/hr_timesheet_report_milestone/readme/DESCRIPTION.rst
odoo/addons/hr_timesheet_report_milestone/readme/USAGE.rst
odoo/addons/hr_timesheet_report_milestone/report/__init__.py
odoo/addons/hr_timesheet_report_milestone/report/hr_timesheet_report.py
odoo/addons/hr_timesheet_report_milestone/static/description/icon.png
odoo/addons/hr_timesheet_report_milestone/static/description/index.html
odoo/addons/hr_timesheet_report_milestone/tests/__init__.py
odoo/addons/hr_timesheet_report_milestone/tests/test_hr_timesheet_report_milestone.py
odoo/addons/hr_timesheet_report_milestone/wizards/__init__.py
odoo/addons/hr_timesheet_report_milestone/wizards/hr_timesheet_report_wizard.py
odoo/addons/hr_timesheet_report_milestone/wizards/hr_timesheet_report_wizard.xml
odoo14_addon_hr_timesheet_report_milestone-14.0.1.0.1.dev10.dist-info/METADATA
odoo14_addon_hr_timesheet_report_milestone-14.0.1.0.1.dev10.dist-info/WHEEL
odoo14_addon_hr_timesheet_report_milestone-14.0.1.0.1.dev10.dist-info/top_level.txt
odoo14_addon_hr_timesheet_report_milestone-14.0.1.0.1.dev10.dist-info/RECORD
